MANIFEST.in
README.md
setup.py
ForMark/ForApp.py
ForMark/ForException.py
ForMark/ForFile.py
ForMark/ForGlobalData.py
ForMark/ForJsonify.py
ForMark/ForLog.py
ForMark/ForMimeType.py
ForMark/ForMongodbSession.py
ForMark/ForOSSLocalRsaProvide.py
ForMark/ForParams.py
ForMark/ForPath.py
ForMark/ForPermission.py
ForMark/ForQRCode.py
ForMark/ForRequests.py
ForMark/ForString.py
ForMark/ForTLSSigAPIv2.py
ForMark/ForTime.py
ForMark/ForWechat.py
ForMark/__init__.py
ForMark/globals.py
ForMark/singleton.py
ForMark/test.py
ForMark.egg-info/PKG-INFO
ForMark.egg-info/SOURCES.txt
ForMark.egg-info/dependency_links.txt
ForMark.egg-info/requires.txt
ForMark.egg-info/top_level.txt
ForMark/bp/__init__.py
ForMark/bp/user.py
ForMark/flask_session/__init__.py
ForMark/flask_session/sessions.py
ForMark/mark_sanic/__init__.py
ForMark/mark_sanic/s1.py
ForMark/model/__init__.py
ForMark/model/basedb.py
ForMark/model/foot.py
ForMark/model/session.py