Metadata-Version: 1.0
Name: ForMark
Version: 1.1.26
Summary: 工具类整理
Home-page: https://github.com/zhaolixiang/ForMark
Author: Mark
Author-email: 1782980833@qq.com
License: MIT Licence
Keywords: pip,ForMark,mark
Platform: any
